yerri/__init__.py
yerri-0.0.1.dist-info/LICENSE
yerri-0.0.1.dist-info/METADATA
yerri-0.0.1.dist-info/WHEEL
yerri-0.0.1.dist-info/top_level.txt
yerri-0.0.1.dist-info/RECORD
